s3_module_loader/__init__.py
s3_module_loader/s3_finder.py
s3_module_loader/s3_loader.py
s3_module_loader-0.2.dist-info/METADATA
s3_module_loader-0.2.dist-info/RECORD
s3_module_loader-0.2.dist-info/WHEEL
s3_module_loader-0.2.dist-info/top_level.txt
